MANIFEST.in
README.rst
pyproject.toml
requirements.txt
setup.cfg
setup.py
ta_captcha_solver/__init__.py
ta_captcha_solver/exceptions.py
ta_captcha_solver/logger.py
ta_captcha_solver/ta_captcha_solver.py
ta_captcha_solver.egg-info/PKG-INFO
ta_captcha_solver.egg-info/SOURCES.txt
ta_captcha_solver.egg-info/dependency_links.txt
ta_captcha_solver.egg-info/entry_points.txt
ta_captcha_solver.egg-info/not-zip-safe
ta_captcha_solver.egg-info/requires.txt
ta_captcha_solver.egg-info/top_level.txt
ta_captcha_solver/browser/__init__.py
ta_captcha_solver/browser/browser.py
ta_captcha_solver/captcha/__init__.py
ta_captcha_solver/captcha/captcha.py
ta_captcha_solver/captcha/cloudflare.py
ta_captcha_solver/captcha/cloudflare_challenge.py
ta_captcha_solver/captcha/fun_captcha.py
ta_captcha_solver/captcha/hcaptcha.py
ta_captcha_solver/captcha/image_captcha.py
ta_captcha_solver/captcha/re_captcha_v2.py
ta_captcha_solver/service_provider/__init__.py
ta_captcha_solver/service_provider/captcha_guru_2_captcha.py
ta_captcha_solver/service_provider/service_provider.py