Metadata-Version: 2.4
Name: ta_captcha_solver
Version: 0.3.7
Summary: Thoughtful Captcha Solver Package
Home-page: https://www.thoughtful.ai/
Author: Bohdan Sukhov
Author-email: bohdan.sukhov@thoughtful.ai
Keywords: ta_captcha_solver
Classifier: Intended Audience :: Developers
Classifier: Natural Language :: English
Classifier: Programming Language :: Python :: 3
Classifier: Programming Language :: Python :: 3.8
Classifier: Programming Language :: Python :: 3.9
Requires-Python: >=3.8
Requires-Dist: requests>=2.26.0
Requires-Dist: retry~=0.9.2
Requires-Dist: rpaframework>=20.0.2
Requires-Dist: setuptools>=65.5.1
Requires-Dist: 2captcha-python==1.2.2
Dynamic: author
Dynamic: author-email
Dynamic: classifier
Dynamic: description
Dynamic: home-page
Dynamic: keywords
Dynamic: requires-dist
Dynamic: requires-python
Dynamic: summary
